peru_dnie/__init__.py
peru_dnie/apdu.py
peru_dnie/card.py
peru_dnie/card_init.py
peru_dnie/cli.py
peru_dnie/cli_config.py
peru_dnie/constants.py
peru_dnie/context.py
peru_dnie/exceptions.py
peru_dnie/hashes.py
peru_dnie/i18n.py
peru_dnie/pyscard.py
peru_dnie/commands/certificate.py
peru_dnie/commands/general.py
peru_dnie/commands/signature.py
peru_dnie-0.0.2.dist-info/METADATA
peru_dnie-0.0.2.dist-info/WHEEL
peru_dnie-0.0.2.dist-info/entry_points.txt
peru_dnie-0.0.2.dist-info/licenses/LICENSE
peru_dnie-0.0.2.dist-info/RECORD
