Metadata-Version: 2.3
Name: peru-dnie
Version: 0.0.2
Project-URL: Homepage, https://github.com/edeustua/peru-dnie
Project-URL: Issues, https://github.com/edeustua/peru-dnie/issues
Author-email: Emiliano Deustua <edeustua@gmail.com>
License-File: LICENSE
Classifier: License :: OSI Approved :: MIT License
Classifier: Operating System :: OS Independent
Classifier: Programming Language :: Python :: 3
Requires-Python: >=3.8
Requires-Dist: attrs~=23.2.0
Requires-Dist: pyscard~=2.0.7
Requires-Dist: rich~=13.7.0
